gps3/__init__.py
gps3/agps3.py
gps3/agps3threaded.py
gps3/gps3.py
gps3/misc.py
gps3-0.33.2.data/data/share/gps3/examples/agegps3.py
gps3-0.33.2.data/data/share/gps3/examples/ahuman.py
gps3-0.33.2.data/data/share/gps3/examples/gegps3.py
gps3-0.33.2.data/data/share/gps3/examples/human.py
gps3-0.33.2.data/data/share/gps3/examples/thread_example.py
gps3-0.33.2.dist-info/DESCRIPTION.rst
gps3-0.33.2.dist-info/METADATA
gps3-0.33.2.dist-info/RECORD
gps3-0.33.2.dist-info/WHEEL
gps3-0.33.2.dist-info/metadata.json
gps3-0.33.2.dist-info/top_level.txt
